guiq/__init__.py
guiq/guiq.py
guiq-0.0.1.dist-info/METADATA
guiq-0.0.1.dist-info/WHEEL
guiq-0.0.1.dist-info/top_level.txt
guiq-0.0.1.dist-info/RECORD
