Metadata-Version: 2.1
Name: guiq
Version: 0.0.1
Summary: Creating GUI designs on the fly
Author: multi-threaded (Matt Goyer)
Author-email: matthew.goyer1@gmail.com
Keywords: python,gui,simple,gui designer
Classifier: Development Status :: 1 - Planning
Classifier: Intended Audience :: Developers
Classifier: Programming Language :: Python :: 3
Classifier: Operating System :: Unix
Classifier: Operating System :: MacOS :: MacOS X
Classifier: Operating System :: Microsoft :: Windows
